[{
    "key": "group_68d28f0c82ff4",
    "title": "Time",
    "fields": [
        {
            "key": "field_68d28f0c845d0",
            "label": "Occasions",
            "name": "occasions",
            "aria-label": "",
            "type": "repeater",
            "instructions": "When is the event scheduled to take place? You have the option to establish a recurring schedule or specify up to 10 distinct dates and times.",
            "required": 1,
            "conditional_logic": 0,
            "wrapper": {
                "width": "",
                "class": "",
                "id": ""
            },
            "is_publicly_hidden": 0,
            "is_privately_hidden": 0,
            "layout": "block",
            "pagination": 0,
            "min": 1,
            "max": 10,
            "collapsed": "",
            "button_label": "Add occation",
            "rows_per_page": 20,
            "sub_fields": [
                {
                    "key": "field_68d28f0c8845b",
                    "label": "Repeat",
                    "name": "repeat",
                    "aria-label": "",
                    "type": "button_group",
                    "instructions": "",
                    "required": 1,
                    "conditional_logic": 0,
                    "wrapper": {
                        "width": "",
                        "class": "",
                        "id": ""
                    },
                    "is_publicly_hidden": 0,
                    "is_privately_hidden": 0,
                    "choices": {
                        "no": "No",
                        "byWeek": "Weekly occasion"
                    },
                    "default_value": "no",
                    "return_format": "value",
                    "allow_null": 0,
                    "allow_in_bindings": 0,
                    "layout": "horizontal",
                    "parent_repeater": "field_68d28f0c845d0"
                },
                {
                    "key": "field_68d28f0c887c5",
                    "label": "Every",
                    "name": "weeksInterval",
                    "aria-label": "",
                    "type": "number",
                    "instructions": "",
                    "required": 1,
                    "conditional_logic": [
                        [
                            {
                                "field": "field_68d28f0c8845b",
                                "operator": "==",
                                "value": "byWeek"
                            }
                        ]
                    ],
                    "wrapper": {
                        "width": "50",
                        "class": "",
                        "id": ""
                    },
                    "default_value": 1,
                    "min": 1,
                    "max": "",
                    "placeholder": "",
                    "step": "",
                    "prepend": "",
                    "append": "week\/weeks",
                    "parent_repeater": "field_68d28f0c845d0"
                },
                {
                    "key": "field_68d28f0c88f84",
                    "label": "Day",
                    "name": "weekDays",
                    "aria-label": "",
                    "type": "checkbox",
                    "instructions": "",
                    "required": 1,
                    "conditional_logic": [
                        [
                            {
                                "field": "field_68d28f0c8845b",
                                "operator": "==",
                                "value": "byWeek"
                            }
                        ]
                    ],
                    "wrapper": {
                        "width": "50",
                        "class": "",
                        "id": ""
                    },
                    "choices": {
                        "https:\/\/schema.org\/Monday": "Mon",
                        "https:\/\/schema.org\/Tuesday": "Tue",
                        "https:\/\/schema.org\/Wednesday": "Wed",
                        "https:\/\/schema.org\/Thursday": "Thu",
                        "https:\/\/schema.org\/Friday": "Fri",
                        "https:\/\/schema.org\/Saturday": "Sat",
                        "https:\/\/schema.org\/Sunday": "Sun"
                    },
                    "default_value": [],
                    "return_format": "value",
                    "allow_custom": 0,
                    "layout": "horizontal",
                    "toggle": 0,
                    "save_custom": 0,
                    "custom_choice_button_text": "L\u00e4gg till nytt val",
                    "parent_repeater": "field_68d28f0c845d0"
                },
                {
                    "key": "field_68d28f0c89b49",
                    "label": "Date",
                    "name": "date",
                    "aria-label": "",
                    "type": "date_picker",
                    "instructions": "",
                    "required": 1,
                    "conditional_logic": 0,
                    "wrapper": {
                        "width": "25",
                        "class": "",
                        "id": ""
                    },
                    "display_format": "Y-m-d",
                    "return_format": "Y-m-d",
                    "first_day": 1,
                    "parent_repeater": "field_68d28f0c845d0",
                    "default_to_current_date": 0
                },
                {
                    "key": "field_68d28f0c8a008",
                    "label": "Until Date",
                    "name": "untilDate",
                    "aria-label": "",
                    "type": "date_picker",
                    "instructions": "",
                    "required": 1,
                    "conditional_logic": [
                        [
                            {
                                "field": "field_68d28f0c8845b",
                                "operator": "!=",
                                "value": "no"
                            }
                        ]
                    ],
                    "wrapper": {
                        "width": "25",
                        "class": "",
                        "id": ""
                    },
                    "display_format": "Y-m-d",
                    "return_format": "Y-m-d",
                    "first_day": 1,
                    "parent_repeater": "field_68d28f0c845d0",
                    "default_to_current_date": 0
                },
                {
                    "key": "field_68d28f0c8a391",
                    "label": "Start time",
                    "name": "startTime",
                    "aria-label": "",
                    "type": "time_picker",
                    "instructions": "",
                    "required": 1,
                    "conditional_logic": 0,
                    "wrapper": {
                        "width": "25",
                        "class": "",
                        "id": ""
                    },
                    "display_format": "H:i:s",
                    "return_format": "H:i:s",
                    "parent_repeater": "field_68d28f0c845d0"
                },
                {
                    "key": "field_68d28f0c8a6ff",
                    "label": "End time",
                    "name": "endTime",
                    "aria-label": "",
                    "type": "time_picker",
                    "instructions": "",
                    "required": 1,
                    "conditional_logic": 0,
                    "wrapper": {
                        "width": "25",
                        "class": "",
                        "id": ""
                    },
                    "display_format": "H:i:s",
                    "return_format": "H:i:s",
                    "parent_repeater": "field_68d28f0c845d0"
                },
                {
                    "key": "field_68d28f0c8abbe",
                    "label": "Booking page URL",
                    "name": "url",
                    "aria-label": "",
                    "type": "url",
                    "instructions": "",
                    "required": 0,
                    "conditional_logic": 0,
                    "wrapper": {
                        "width": "",
                        "class": "",
                        "id": ""
                    },
                    "default_value": "",
                    "placeholder": "",
                    "parent_repeater": "field_68d28f0c845d0"
                },
                {
                    "key": "field_68dd084d90dc7",
                    "label": "Description",
                    "name": "description",
                    "aria-label": "",
                    "type": "wysiwyg",
                    "instructions": "Specific information about this occasion",
                    "required": 0,
                    "conditional_logic": [
                        [
                            {
                                "field": "field_68d28f0c8845b",
                                "operator": "==",
                                "value": "no"
                            }
                        ]
                    ],
                    "wrapper": {
                        "width": "",
                        "class": "",
                        "id": ""
                    },
                    "is_publicly_hidden": 0,
                    "is_privately_hidden": 0,
                    "default_value": "",
                    "allow_in_bindings": 0,
                    "tabs": "all",
                    "toolbar": "basic",
                    "media_upload": 0,
                    "delay": 1,
                    "parent_repeater": "field_68d28f0c845d0"
                }
            ]
        }
    ],
    "location": [
        [
            {
                "param": "post_type",
                "operator": "==",
                "value": "event"
            }
        ]
    ],
    "menu_order": 3,
    "position": "acf_after_title",
    "style": "default",
    "label_placement": "left",
    "instruction_placement": "label",
    "hide_on_screen": [
        "permalink",
        "the_content",
        "excerpt",
        "discussion",
        "comments",
        "slug",
        "format",
        "page_attributes",
        "featured_image",
        "categories",
        "tags",
        "send-trackbacks"
    ],
    "active": true,
    "description": "",
    "show_in_rest": 1,
    "display_title": "",
    "allow_ai_access": false,
    "ai_description": ""
}]
